demod/__init__.py
demod/helpers.py
demod/datasets/__init__.py
demod/datasets/base_loader.py
demod/datasets/tou_loader.py
demod/datasets/CREST/__init__.py
demod/datasets/CREST/loader.py
demod/datasets/CREST/utils.py
demod/datasets/DESTATIS/__init__.py
demod/datasets/DESTATIS/loader.py
demod/datasets/ExampleData/__init__.py
demod/datasets/ExampleData/example_loader.py
demod/datasets/ExcellInputFile/__init__.py
demod/datasets/ExcellInputFile/loader.py
demod/datasets/FfE_Open_Data/__init__.py
demod/datasets/GermanTOU/__init__.py
demod/datasets/GermanTOU/create_zip.py
demod/datasets/GermanTOU/loader.py
demod/datasets/GermanTOU/parser.py
demod/datasets/Germany/__init__.py
demod/datasets/Germany/loader.py
demod/datasets/OpenPowerSystems/__init__.py
demod/datasets/OpenPowerSystems/loader.py
demod/datasets/RenewablesNinja/__init__.py
demod/datasets/RenewablesNinja/loader.py
demod/datasets/tracebase/__init__.py
demod/datasets/tracebase/loader.py
demod/metrics/__init__.py
demod/metrics/errors.py
demod/metrics/loads.py
demod/metrics/states.py
demod/simulators/__init__.py
demod/simulators/activity_simulators.py
demod/simulators/appliance_simulators.py
demod/simulators/base_simulators.py
demod/simulators/car_simulator.py
demod/simulators/crest_simulators.py
demod/simulators/heating_simulators.py
demod/simulators/lighting_simulators.py
demod/simulators/load_simulators.py
demod/simulators/sparse_simulators.py
demod/simulators/util.py
demod/simulators/weather_simulators.py
demod/utils/__init__.py
demod/utils/appliances.py
demod/utils/cards_doc.py
demod/utils/converters.py
demod/utils/countries.py
demod/utils/data_types.py
demod/utils/distribution_functions.py
demod/utils/error_messages.py
demod/utils/monte_carlo.py
demod/utils/parse_helpers.py
demod/utils/plotters.py
demod/utils/sim_types.py
demod/utils/sparse.py
demod/utils/subgroup_handling.py
tests/__init__.py
tests/context.py
tests/test_CDFfunctions.py
tests/test_activity_simulators.py
tests/test_appliance_simulators.py
demod-0.2.post1.dist-info/LICENSE.txt
demod-0.2.post1.dist-info/METADATA
demod-0.2.post1.dist-info/WHEEL
demod-0.2.post1.dist-info/top_level.txt
demod-0.2.post1.dist-info/RECORD
