Metadata-Version: 2.1
Name: demod
Version: 0.2.post1
Summary: Domestic Energy Demand Modelling Library
Home-page: https://github.com/epfl-herus/demod
Author: Matteo Barsanti, Lionel Constantin, HERUS, Ecole Polytechnique Fédérale de Lausanne
Author-email: demod@groupes.epfl.ch
License: GNU General Public License v3 (GPLv3)
Project-URL: Documentation, https://demod.readthedocs.io/
Keywords: energy,demand,simulation,modelling,load,electricity,power,appliance,heating,household,DSM,dataset
Platform: UNKNOWN
Classifier: Development Status :: 4 - Beta
Classifier: Programming Language :: Python :: 3
Classifier: Programming Language :: Python :: 3.8
Classifier: Programming Language :: Python :: 3.9
Classifier: Programming Language :: Python :: 3.10
Classifier: Operating System :: OS Independent
Classifier: License :: OSI Approved :: GNU General Public License v3 (GPLv3)
Classifier: Intended Audience :: Science/Research
Classifier: Topic :: Software Development :: Libraries :: Python Modules
Classifier: Topic :: Scientific/Engineering
Requires-Python: >=3.8
License-File: LICENSE.txt
Requires-Dist: numpy (>=1.19)
Requires-Dist: scipy (>=1.4)
Requires-Dist: pandas (>=1.2)
Requires-Dist: matplotlib (>=3.4)
